<?xml version="1.0" encoding="utf-8"?><Search><pages Count="5"><page Index="1"><![CDATA[O.1.            The administrative personnel/staff have


                        commendable performance.]]></page><page Index="2"><![CDATA[CvSU ANNUAL REPORT 2017-2021


         https://drive.google.com/drive/folders/10-EV88wImyYNQUVUpQgnSVtbuBc0SxJm?usp=sharing
















                                 CvSU TANZA CAMPUS


                           ANNUAL REPORT 2018 - 2021


          https://drive.google.com/drive/folders/1DbNmAv13zuXPELydaKdmFh8I4IK8hzK8?usp=sharing



















                                 CvSU TANZA CAMPUS


                            ACCOMPLISHMENT REPORT


          https://drive.google.com/drive/folders/1-pGfW1cBLq4UtMosKBFTXoO69T34GnJP?usp=sharing]]></page><page Index="3"><![CDATA[INDIVIDUAL PERFORMANCE


                  COMMITMENT RATINGS 2018 - 2022



             https://drive.google.com/drive/folders/1tdiniqH4jyYLJr9sG2XYfa8BHnYjSXEr?usp=sharing





















                                OFFICE PERFORMANCE


                            COMMITMENT AND REVIEW


                                          2017 - 2022


           https://drive.google.com/drive/folders/1x7d0qdNAAM2dSL9b33L7VaGK1iSrLjbT?usp=sharing]]></page><page Index="4"><![CDATA[]]></page><page Index="5"><![CDATA[]]></page></pages></Search>