<?xml version="1.0" encoding="utf-8"?><Search><pages Count="6"><page Index="1"><![CDATA[AREA VIII












               PHYSICAL PLANT






                   AND FACILITIES]]></page><page Index="2"><![CDATA[PARAMETER I












                 ACCREDITATION





                                       CENTER]]></page><page Index="3"><![CDATA[OUTCOME/S]]></page><page Index="4"><![CDATA[O.1.            The AC is well-equipped and managed.]]></page><page Index="5"><![CDATA[The support office is furnished with necessary

                       equipment, supplies and materials.]]></page><page Index="6"><![CDATA[QUALITY ASSURANCE AND ACCREDITATION OFFICE]]></page></pages></Search>